bioexperiment_suite/__init__.py
bioexperiment_suite/device_interfaces.json
bioexperiment_suite/experiment/__init__.py
bioexperiment_suite/experiment/actions.py
bioexperiment_suite/experiment/collections.py
bioexperiment_suite/experiment/experiment.py
bioexperiment_suite/gui/__init__.py
bioexperiment_suite/gui/device_widgets.py
bioexperiment_suite/gui/devices_tab.py
bioexperiment_suite/gui/experiment_tab.py
bioexperiment_suite/gui/main.py
bioexperiment_suite/gui/store.py
bioexperiment_suite/interfaces/__init__.py
bioexperiment_suite/interfaces/pump.py
bioexperiment_suite/interfaces/serial_connection.py
bioexperiment_suite/interfaces/spectrophotometer.py
bioexperiment_suite/loader.py
bioexperiment_suite/py.typed
bioexperiment_suite/settings.py
bioexperiment_suite/tools/__init__.py
bioexperiment_suite/tools/devices.py
bioexperiment_suite/tools/serial_port.py
bioexperiment_suite-0.5.0.dist-info/LICENSE
bioexperiment_suite-0.5.0.dist-info/METADATA
bioexperiment_suite-0.5.0.dist-info/WHEEL
bioexperiment_suite-0.5.0.dist-info/entry_points.txt
bioexperiment_suite-0.5.0.dist-info/RECORD
