Metadata-Version: 2.1
Name: bioexperiment-suite
Version: 0.5.0
Summary: Python toolbox for managing biological experiment devices including pumps, cell density detectors, thermometers, and other related equipment.
Home-page: https://github.com/denis240997/bio_tools
License: MIT
Author: Denis Khamitov
Author-email: hamitov.97@mail.ru
Requires-Python: >=3.12,<3.13
Classifier: License :: OSI Approved :: MIT License
Classifier: Programming Language :: Python :: 3
Classifier: Programming Language :: Python :: 3.12
Provides-Extra: gui
Provides-Extra: websocket
Requires-Dist: loguru (>=0.7.2,<0.8.0)
Requires-Dist: munch (>=4.0.0,<5.0.0)
Requires-Dist: pyserial (>=3.5,<4.0)
Requires-Dist: python-dotenv (>=1.0.1,<2.0.0)
Requires-Dist: ttkbootstrap (>=1.10.1,<2.0.0) ; extra == "gui"
Requires-Dist: websockets (>=14.0,<15.0) ; extra == "websocket"
Project-URL: Repository, https://github.com/denis240997/bio_tools
